operator_csv_libs/__init__.py
operator_csv_libs/catalog.py
operator_csv_libs/crd.py
operator_csv_libs/csv.py
operator_csv_libs/deployment.py
operator_csv_libs/imagerepo.py
operator_csv_libs/images.py
operator_csv_libs/operatorimage.py
operator_csv_libs/package.py
operator_csv_libs-1.9.31.dist-info/METADATA
operator_csv_libs-1.9.31.dist-info/WHEEL
operator_csv_libs-1.9.31.dist-info/top_level.txt
operator_csv_libs-1.9.31.dist-info/RECORD
