Metadata-Version: 2.1
Name: operator-csv-libs
Version: 1.9.31
Summary: Code to manage OLM related CSVs and channels
Home-page: https://github.com/multicloud-ops/operator-csv-libs
Author: bennett-white
Requires-Dist: requests ==2.28.1
Requires-Dist: pyyaml ==6.0.1
Requires-Dist: pygithub ==1.55
Requires-Dist: dohq-artifactory ==0.8.4
Requires-Dist: natsort ==8.3.1
